setup.py
japaneselogger/__init__.py
japaneselogger.egg-info/PKG-INFO
japaneselogger.egg-info/SOURCES.txt
japaneselogger.egg-info/dependency_links.txt
japaneselogger.egg-info/top_level.txt