Metadata-Version: 1.0
Name: japaneselogger
Version: 0.1.1
Summary: 日本人向けのログ作成ライブラリ
Home-page: UNKNOWN
Author: UNKNOWN
Author-email: UNKNOWN
License: UNKNOWN
Platform: UNKNOWN
